{"ts":"2024-08-25T00:40:18.490Z","level":"error","error":{"originalError":{"name":"NotFound","message":"{\n  \"status\": 404,\n  \"statusText\": \"Not Found\",\n  \"message\": \"The resource could not be found.\",\n  \"details\": {\n    \"type\": \"Space\",\n    \"id\": \"1612cm5jnx\"\n  },\n  \"request\": {\n    \"url\": \"/spaces/1612cm5jnx\",\n    \"headers\": {\n      \"Accept\": \"application/json, text/plain, */*\",\n      \"Content-Type\": \"application/vnd.contentful.management.v1+json\",\n      \"X-Contentful-User-Agent\": \"app contentful.cli/3.3.7; feature space-export; sdk contentful-management.js/11.31.6; platform node.js/v22.7.0; os macOS/v22.7.0;\",\n      \"CF-Sequence\": \"1da45053-2000-4bae-84ba-d500c68f4487\",\n      \"Authorization\": \"Bearer ...rutrc\",\n      \"User-Agent\": \"axios/1.7.4\",\n      \"Accept-Encoding\": \"gzip, compress, deflate, br\"\n    },\n    \"method\": \"get\"\n  },\n  \"requestId\": \"f03710ac-5763-46fc-8912-018c44e124e6\"\n}"},"data":{"status":404,"statusText":"Not Found","message":"The resource could not be found.","details":{"type":"Space","id":"1612cm5jnx"},"request":{"url":"/spaces/1612cm5jnx","headers":{"Accept":"application/json, text/plain, */*","Content-Type":"application/vnd.contentful.management.v1+json","X-Contentful-User-Agent":"app contentful.cli/3.3.7; feature space-export; sdk contentful-management.js/11.31.6; platform node.js/v22.7.0; os macOS/v22.7.0;","CF-Sequence":"1da45053-2000-4bae-84ba-d500c68f4487","Authorization":"Bearer ...rutrc","User-Agent":"axios/1.7.4","Accept-Encoding":"gzip, compress, deflate, br"},"method":"get"},"requestId":"f03710ac-5763-46fc-8912-018c44e124e6"}}}